README
setup.cfg
setup.py
scripts/stellaris-client
stellaris/__init__.py
stellaris.client.egg-info/PKG-INFO
stellaris.client.egg-info/SOURCES.txt
stellaris.client.egg-info/dependency_links.txt
stellaris.client.egg-info/namespace_packages.txt
stellaris.client.egg-info/not-zip-safe
stellaris.client.egg-info/requires.txt
stellaris.client.egg-info/top_level.txt
stellaris/client/__init__.py
stellaris/client/client.py
stellaris/client/console.py
stellaris/client/parsers.py