Metadata-Version: 1.0
Name: stellaris.client
Version: 0.1.2
Summary: A StellarIS client package.
Home-page: http://stellaris.zib.de/
Author: Mikael Hoegqvist
Author-email: hoegqvist@zib.de
License: Apache 2.0
Platform: UNKNOWN
Classifier: Development Status :: 4 - Beta
Classifier: Environment :: Web Environment
Classifier: Programming Language :: Python
Classifier: Topic :: Internet :: WWW/HTTP
Classifier: Topic :: Software Development :: Libraries
